flask_environment_manager/__init__.py
flask_environment_manager/os_environment_manager.py
flask_environment_manager/ssm_environment_manager.py
flask_environment_manager/whitelist_parser.py
flask_environment_manager-2.4.0.dist-info/LICENSE
flask_environment_manager-2.4.0.dist-info/METADATA
flask_environment_manager-2.4.0.dist-info/WHEEL
flask_environment_manager-2.4.0.dist-info/top_level.txt
flask_environment_manager-2.4.0.dist-info/RECORD
