Metadata-Version: 2.1
Name: flask-environment-manager
Version: 2.4.0
Summary: An environment manager for Flask, with support for whitelists and AWS SSM.
Home-page: https://github.com/ScholarPack/flask-environment-manager
Author: ScholarPack
Author-email: dev@scholarpack.com
License: UNKNOWN
Platform: UNKNOWN
Classifier: Development Status :: 5 - Production/Stable 
Classifier: Programming Language :: Python :: 3
Classifier: License :: OSI Approved :: MIT License
Classifier: Operating System :: OS Independent
Requires-Python: >=3.8
Requires-Dist: flask
Requires-Dist: boto3
Requires-Dist: beautifultable
